code/markov/markov.v
`timescale 1ns/1ps
module trng (
    input clk,
    input reset,
	input latch_bit,
	
	output out_valid,
    output out
);

	wire [3:0] lane;
	markov16 router(
		.clk(clk),
		.reset(reset),
		.bit_in(latch_bit),
		.lane(lane),
		.bit_out()
	);

	wire [5:0] ivn_out;
	wire [5:0] ivn_valid;
	ivn_top ivn (
		.clk(clk),
		.reset(reset),
		.lane(lane),
		.s(latch_bit),  // gets the same bit as the markov router
		.s_valid(1'b1),
		.s_vn(ivn_out),
		.s_vn_valid(ivn_valid)
	);

	wire buffer_valid;
	wire [16:0] buffer_out;
	fifo16 buffer(
		.clk(clk),
		.reset(reset),
		.valid(ivn_valid),
		.bits(ivn_out),
		
		.out_valid(buffer_valid),
		.out_16(out_16),
	);

	lfsr16 lfsr(
		.clk(clk),
		.reset(reset || buffer_valid),
		.in_bits(buffer_out),
		.out_bit(out)  
	);
	
	reg trng_valid;
	always @(posedge clk) begin
		trng_valid <= buffer_valid;
	end
	assign out_valid = trng_valid;

endmodule

///////////////////////////////////////////////////////////////////////
/////       SUB-BLOCKS
///////////////////////////////////////////////////////////////////////

module markov16(
    input clk,
    input reset,
    input bit_in,
    output [3:0] lane,
    output bit_out
);

reg [3:0] state;
reg [3:0] next_state;

assign bit_out = bit_in;
assign lane = state;

always @(*) begin
    next_state ={state[2:0], bit_in};
end

always@(posedge clk) begin
    if (reset) begin
        state <= 4'b0;
        next_state <= 4'b0;
    end else begin
        state <= next_state;
    end
end
endmodule

module fifo16(
	input clk,
	input reset,
	input [5:0] valid,
	input [5:0] bits,
	
	output out_valid,
	output [15:0] out_16
);
	reg [20:0] register;
	reg [4:0] counter;
	wire [4:0] counter_wire;
	wire [4:0] counter_up;
	reg out_valid_reg;
	
	//count number of valid bits	
	reg [2:0] num_valid;
	reg [2:0] num_valid_n;
	reg [5:0] valid_bits;
	reg [5:0] write_bits;
	integer idx;
	always @(*) begin
		num_valid= {2{1'b0}};
		valid_bits = {5{1'b0}};
		for( idx = 0; idx<6; idx=idx+1) begin
			num_valid = num_valid + valid[idx];
			valid_bits[num_valid-1] = valid[idx] ?  bits[idx] : valid_bits[num_valid-1];
		end
		num_valid_n = 6-num_valid;
		write_bits = {{num_valid_n{1'b0}}, valid_bits}; 
	end
	assign  writing = write_bits;
	
	integer i;
	integer j;
	reg out_16_reg;
	always @(posedge clk) begin
		if (reset == 1) begin
			counter<=0;
			register <= 16'b0;
			out_valid_reg <= 0;
		end
		else if (counter_wire >= 15) begin
			counter <= (|valid) ? (counter_wire + num_valid -15): (counter_wire - 15);
			for (i=15; i<20; i=i+1) begin
				register[i-15] <= register[i+1];
			end
			for (j=0; j<num_valid; j=j+1) begin
				register[counter_wire - 15 + j] <= write_bits[j];
			end
			for (j = counter_wire + num_valid -15; j<21; j=j+1) begin
				register[j] <= 0;
			end
			out_valid_reg <= 0;
		end		
		else begin 		
			for (j=0; j<num_valid; j=j+1) begin
				register[counter_wire + j] <= write_bits[j];
			end
			counter <= (|valid) ? (counter_wire + num_valid) : counter;
			out_valid_reg <= ((|valid) & (counter_wire + num_valid) > 15) ? 1 : 0;
		end
	end
	assign counter_wire = reset? 0 :counter;
	assign counter_up = reset? 0 :counter+5;
	assign out_16 = reset ? 0 :register[15:0];
	assign out_valid = reset ? 0 :out_valid_reg;

endmodule

module lfsr16(
    input clk,
    input reset,
    input [15:0] in_bits,
    output out_bit    
);
    reg [15:0] register;
    wire xor_bit;
    assign out_bit = register[0];
    assign xor_bit = ((register[15] ^ register[13]) ^ register[12]) ^ register[10];
    always @(posedge clk) begin
        if (reset) begin
            register <= in_bits;
        end else begin
            register <= {register[15:1], xor_bit };
        end
    end
endmodule

code/markov/fifo_test.v
`timescale 1ns/1ps

module mc_tester();
    reg clk;
    reg reset;
    reg [5:0] valid;
    reg [5:0] bits;

    wire out_valid;
    wire [15:0] out;
    initial clk = 0;
    initial reset =0;
    always #(10) clk <= ~clk;
    wire [5:0] writing;

    fifo16 dut (.clk(clk), .reset(reset), .valid(valid),
    .bits(bits), .out_valid(out_valid), .out_16(out), .writing(writing)
    );

    initial begin
        $dumpfile("fifo_test.vcd");
        $dumpvars(0, dut);
        $display("start sim");
        @(posedge clk);
        reset = 1;
		#1;
        @(posedge clk) begin
			reset = 0;
            bits = 6'b0;
            valid = 6'b0;
        end
        #1;
        $display("in: %b, out_valid: %b, out: %b", bits, out_valid, out);

        @(posedge clk) begin
            bits =  6'b111111;
            valid = 6'b011111;
        end
        #1;
        $display("in: %b, out_valid: %b, out: %b, writing: %b", bits, out_valid, out, writing);

        @(posedge clk) begin
            bits =  6'b010001;
            valid = 6'b100111;
        end
        #1;
        $display("in: %b, out_valid: %b, out: %b", bits, out_valid, out);

        @(posedge clk) begin
            bits =  6'b010101;
            valid = 6'b110111;
        end
        #1;
        $display("in: %b, out_valid: %b, out: %b", bits, out_valid, out);
		
		@(posedge clk) begin
            bits =  6'b110101;
            valid = 6'b110111;
        end
        #1;
        $display("in: %b, out_valid: %b, out: %b", bits, out_valid, out);
        
        @(posedge clk) begin
            bits =  6'b110101;
            valid = 6'b100110;
        end
        #1;
        $display("in: %b, out_valid: %b, out: %b", bits, out_valid, out);
        #20;
        $display("in: %b, out_valid: %b, out: %b", bits, out_valid, out);
                #20;
        $display("in: %b, out_valid: %b, out: %b", bits, out_valid, out);
        #20 $finish();
    end

endmodule

code/markov/fifo_test.vcd
$date
	Tue May  4 19:26:43 2021
$end

$version
	Synopsys VCS version P-2019.06
$end

$timescale
	1ps
$end

$comment Csum: 1 17a8035aee561473 $end


$scope module mc_tester $end

$scope module dut $end
$var wire 1 ! clk $end
$var wire 1 " reset $end
$var wire 6 # valid [5:0] $end
$var wire 6 $ bits [5:0] $end
$var wire 1 % out_valid $end
$var wire 16 & out_16 [15:0] $end
$var wire 6 ' writing [5:0] $end
$var reg 21 ( register [20:0] $end
$var reg 5 ) counter [4:0] $end
$var wire 5 * counter_wire [4:0] $end
$var wire 5 + counter_up [4:0] $end
$var reg 1 , out_valid_reg $end
$var reg 3 - num_valid [2:0] $end
$var reg 3 . num_valid_n [2:0] $end
$var reg 6 / valid_bits [5:0] $end
$var reg 6 0 write_bits [5:0] $end
$var integer 32 1 idx $end
$var integer 32 2 i $end
$var integer 32 3 j $end
$var reg 1 4 out_16_reg $end
$upscope $end

$upscope $end

$enddefinitions $end

#0
$dumpvars
x,
bxxxxx )
bxxxxx *
bxxxxxxxxxxxxxxxxxxxxxxxxxxxxxxxx 2
bxxxxxxxxxxxxxxxxxxxxxxxxxxxxxxxx 1
bxxxxxxxxxxxxxxxxxxxxxxxxxxxxxxxx 3
bxxx -
bxxx .
bxxxxxxxxxxxxxxxxxxxxx (
bxxxxx +
bxxxxxx /
bxxxxxx 0
x4
0!
0"
bxxxxxx #
bxxxxxx $
x%
bxxxxxxxxxxxxxxxx &
bxxxxxx '
$end
#10000
1!
1"
b00000 +
0%
b0000000000000000 &
b00000 *
b000000000000000000000 (
b00000 )
0,
#20000
0!
#30000
1!
0"
b00101 +
b000000 $
b000000 #
b00000000000000000000000000000000 3
b000 -
b000000 /
b110 .
b000000 0
b000000 '
b00000000000000000000000000000110 1
#40000
0!
#50000
1!
b111111 $
b011111 #
b101 -
b011111 /
b001 .
b011111 0
b011111 '
#60000
0!
#70000
1!
b010001 $
b100111 #
b00000000000000000000000000000101 3
b100 -
b000001 /
b010 .
b000001 0
b000001 '
b000000000000000011111 (
b0000000000011111 &
b00101 )
b01010 +
b00101 *
#80000
0!
#90000
1!
b010101 $
b110111 #
b00000000000000000000000000000100 3
b101 -
b001101 /
b001 .
b001101 0
b001101 '
b000000000000000111111 (
b0000000000111111 &
b01001 )
b01110 +
b01001 *
#100000
0!
#110000
1!
b110101 $
b00000000000000000000000000000101 3
b011101 /
b011101 0
b011101 '
b000000001101000111111 (
b0001101000111111 &
b01110 )
b10011 +
b01110 *
#120000
0!
#130000
1!
b100110 #
b011 -
b000110 /
b011 .
b000110 0
b000110 '
b001110101101000111111 (
b0101101000111111 &
b10011 )
b11000 +
b10011 *
1,
1%
#140000
0!
#150000
1!
b00000000000000000000000000010100 2
b00000000000000000000000000010101 3
b00111 )
b01100 +
b00111 *
b001110101101000100111 (
b0101101000100111 &
b000000000000001100111 (
b0000000001100111 &
0,
0%
#160000
0!
#170000
1!
b00000000000000000000000000000011 3
b000000000001101100111 (
b0000001101100111 &
b01010 )
b01111 +
b01010 *
#180000
0!
#190000
1!
b000000001101101100111 (
b0001101101100111 &
b01101 )
b10010 +
b01101 *
