code/markov/markov.v
`timescale 1ns/1ps
module trng (
    input clk,
    input reset,
	input latch_bit,
	
	output out_valid,
    output out
);

	wire [3:0] lane;
	markov16 router(
		.clk(clk),
		.reset(reset),
		.bit_in(latch_bit),
		.lane(lane),
		.bit_out()
	);

	wire [5:0] ivn_out;
	wire [5:0] ivn_valid;
	ivn_top ivn (
		.clk(clk),
		.reset(reset),
		.lane(lane),
		.s(latch_bit),  // gets the same bit as the markov router
		.s_valid(1'b1),
		.s_vn(ivn_out),
		.s_vn_valid(ivn_valid)
	);
	

	fifo buffer(
		.clk(clk),
		.reset(reset),
		.valid(ivn_valid),
		.bits(ivn_out),
		
		.out_valid(out_valid),
		.out(out)
	);
	
	/*
	// with lfsr
	wire buffer_valid;
	wire [15:0] buffer_out;
	fifo16 buffer(
		.clk(clk),
		.reset(reset),
		.valid(ivn_valid),
		.bits(ivn_out),
		
		.out_valid(buffer_valid),
		.out_16(buffer_out)
	);
	
	lfsr16 lfsr(
		.clk(clk),
		.reset(reset || buffer_valid),
		.in_bits(buffer_out),
		.out_bit(out)  
	);

	reg flag;
	always @(posedge clk) begin
		if (reset) flag <= 0;
		else flag <= buffer_valid ? 1 : flag;
	end
	assign out_valid = flag;
	*/
endmodule

///////////////////////////////////////////////////////////////////////
/////       SUB-BLOCKS
///////////////////////////////////////////////////////////////////////

module markov16(
    input clk,
    input reset,
    input bit_in,
    output [3:0] lane,
    output bit_out
);

reg [3:0] state;
reg [3:0] next_state;

assign bit_out = bit_in;
assign lane = state;

always @(*) begin
    next_state ={state[2:0], bit_in};
end

always@(posedge clk) begin
    if (reset) begin
        state <= 4'b0;
        next_state <= 4'b0;
    end else begin
        state <= next_state;
    end
end
endmodule

module fifo16(
	input clk,
	input reset,
	input [5:0] valid,
	input [5:0] bits,
	
	output out_valid,
	output [15:0] out_16
);
	reg [20:0] register;
	reg [4:0] counter;
	wire [4:0] counter_wire;
	wire [4:0] counter_up;
	reg out_valid_reg;
	
	//count number of valid bits	
	reg [2:0] num_valid;
	reg [2:0] num_valid_n;
	reg [5:0] valid_bits;
	reg [11:0] write_bits;
	integer idx;
	always @(*) begin
		num_valid= {2{1'b0}};
		valid_bits = {5{1'b0}};
		for( idx = 0; idx<6; idx=idx+1) begin
			num_valid = num_valid + valid[idx];
			valid_bits[num_valid-1] = valid[idx] ?  bits[idx] : valid_bits[num_valid-1];
		end
		num_valid_n = 6-num_valid;
		write_bits = {{6{1'b0}}, valid_bits}; 
	end
	assign  writing = write_bits;
	
	integer i;
	integer j;
	reg out_16_reg;
	always @(posedge clk) begin
		if (reset == 1) begin
			counter<=0;
			register <= 16'b0;
			out_valid_reg <= 0;
		end
		else if (counter_wire >= 15) begin
			counter <= (|valid) ? (counter_wire + num_valid -15): (counter_wire - 15);
			for (i=15; i<20; i=i+1) begin
				register[i-15] <= register[i+1];
			end
			for (j=0; j<num_valid; j=j+1) begin
				register[counter_wire - 15 + j] <= write_bits[j];
			end
			for (j = counter_wire + num_valid -15; j<21; j=j+1) begin
				register[j] <= 0;
			end
			out_valid_reg <= 0;
		end		
		else begin 		
			for (j=0; j<num_valid; j=j+1) begin
				register[counter_wire + j] <= write_bits[j];
			end
			counter <= (|valid) ? (counter_wire + num_valid) : counter;
			out_valid_reg <= ((|valid) & (counter_wire + num_valid) >= 15) ? 1 : 0;
		end
	end
	assign counter_wire = reset? 0 :counter;
	assign counter_up = reset? 0 :counter+5;
	assign out_16 = reset ? 0 :register[15:0];
	assign out_valid = reset ? 0 :out_valid_reg;

endmodule

module lfsr16(
    input clk,
    input reset,
    input [15:0] in_bits,
    output out_bit    
);
    reg [15:0] register;
    wire xor_bit;
    assign out_bit = register[0];
    assign xor_bit = ((register[15] ^ register[13]) ^ register[12]) ^ register[10];
    always @(posedge clk) begin
        if (reset) begin
            register <= in_bits;
        end else begin
            register <= {register[14:0], xor_bit };
        end
    end
endmodule

// Trying to just output bits: 
module fifo(
	input clk,
	input reset,
	input [5:0] valid,
	input [5:0] bits,
	
	output out_valid,
	output out
);
	reg [20:0] register;
	reg [4:0] counter;
	wire [4:0] counter_wire;
	wire [4:0] counter_up;
	reg out_valid_reg;
	
	//count number of valid bits	
	reg [2:0] num_valid;
	reg [2:0] num_valid_n;
	reg [5:0] valid_bits;
	reg [11:0] write_bits;
	integer idx;
	always @(*) begin
		num_valid= {2{1'b0}};
		valid_bits = {5{1'b0}};
		for( idx = 0; idx<6; idx=idx+1) begin
			num_valid = num_valid + valid[idx];
			valid_bits[num_valid-1] = valid[idx] ?  bits[idx] : valid_bits[num_valid-1];
		end
		num_valid_n = 6-num_valid;
		write_bits = {{6{1'b0}}, valid_bits}; 
	end
	assign  writing = write_bits;
	
	integer i;
	integer j;
	reg out_16_reg;
	always @(posedge clk) begin
		if (reset == 1) begin
			counter<=0;
			register <= 21'b0;
			out_valid_reg <= 0;
		end
		/*else if (counter_wire >= 15) begin
			counter <= (|valid) ? (counter_wire + num_valid -15): (counter_wire - 15);
			for (i=15; i<20; i=i+1) begin
				register[i-15] <= register[i+1];
			end
			for (j=0; j<num_valid; j=j+1) begin
				register[counter_wire - 15 + j] <= write_bits[j];
			end
			for (j = counter_wire + num_valid -15; j<21; j=j+1) begin
				register[j] <= 0;
			end
			out_valid_reg <= 0;
		end	
		*/	
		else begin 
			for (j=0; j<counter_wire-1; j=j+1) begin
				register[j] <= register[j+1];
			end
			if (num_valid == 0) register[counter_wire-1] <= 0;
			else begin
				for (j=0; j<num_valid; j=j+1) begin
					if ((counter_wire + j)  < 21)
						register[counter_wire + j] <= write_bits[j];
				end
			end
			
			counter <= (|valid) ? ((counter_wire + num_valid <21) ? (counter_wire + num_valid - 1) : 5'd20)
								: ((counter_wire == 0) ? 0 : counter_wire-1);
			out_valid_reg <= |(counter_wire + num_valid);
		end
	end
	assign counter_wire = reset? 0 :counter;
	assign counter_up = reset? 0 :counter+5;
	assign out = register[0];
	assign out_valid = reset ? 0 :out_valid_reg;

endmodule

code/markov/ivn.v
module ivn_top (
    input clk,
    input reset,
    input [3:0] lane,
    input s,
    input s_valid,
    output [5:0] s_vn,
    output [5:0] s_vn_valid
);
    wire [5:0] s_store;
    wire [5:0] s_valid_store;
    wire [5:0] s_load;
    wire [5:0] s_valid_load;
    reg [3:0] reg_lane;
    // do we need an extra bit for current lane?
    reg [3:0] current_lane;
    reg wen;
    reg load;

    parameter WAIT = 2'd0;
    parameter STORE = 2'd1;
    parameter LOAD = 2'd2;

    reg [1:0] state;
    reg [1:0] next_state;
    always @(*) begin
        case(state) 
        WAIT: begin
            wen = 1'b0;
            load = 1'b0;
            if (current_lane != lane) begin
                next_state = STORE;
            end else begin
                next_state = WAIT;
            end
        end
        STORE: begin
            reg_lane = current_lane;
            wen = 1'b1;
            load = 1'b0;
            next_state = LOAD;
        end
        LOAD: begin
            reg_lane = lane;
            wen = 1'b0;
            load = 1'b1;
            next_state = WAIT;
        end
        endcase
    end
    always @(posedge clk) begin
        if (reset) begin
            state <= WAIT;
            current_lane <= 0;
        end else begin
            state <= next_state;
            if (state == LOAD) begin
                current_lane <= lane;
            end
        end 
    end 
    ivn_register ivn_reg(.clk(clk), .reset(reset), .wen(wen), .lane(reg_lane), .s_store(s_store), .s_valid_store(s_valid_store),
    .s_load(s_load), .s_valid_load(s_valid_load)
    );

    ivn_logic shared_logic(.clk(clk), .reset(reset), .load(load), .s_load(s_load), .s_valid_load(s_valid_load),
    .s(s), .s_valid(s_valid), .s_vn(s_vn), .s_vn_valid(s_vn_valid), .s_store(s_store), .s_valid_store(s_valid_store)
    );

endmodule

module ivn_register (
    input clk,
    input reset,
    input wen,
    input [3:0] lane,
    input [5:0] s_store,
    input [5:0] s_valid_store,
    output [5:0] s_load,
    output [5:0] s_valid_load
);
    reg [11:0] registers [15:0];
    assign s_load = registers[lane][5:0];
    assign s_valid_load = registers[lane][11:6];

    always@(posedge clk) begin
        if (reset) begin
            registers[0] <= 0;
            registers[1] <= 0;
            registers[2] <= 0;
            registers[3] <= 0;
            registers[4] <= 0;
            registers[5] <= 0;
            registers[6] <= 0;
            registers[7] <= 0;
            registers[8] <= 0;
            registers[9] <= 0;
            registers[10] <= 0;
            registers[11] <= 0;
            registers[12] <= 0;
            registers[13] <= 0;
            registers[14] <= 0;
            registers[15] <= 0;
        end
        if (wen) begin
            registers[lane][5:0] <= s_store;
            registers[lane][11:6] <= s_valid_store;
        end
    end
endmodule

// hardcoded 3 levels, 6 pes
module ivn_logic (
    input clk,
    input reset,
    input load,
    input [5:0] s_load,
    input [5:0] s_valid_load,
    input s,
    input s_valid,
    output [5:0] s_store,
    output [5:0] s_valid_store,
    output [5:0] s_vn,
    output [5:0] s_vn_valid
);
    wire [2:0] s_xor;
    wire [2:0] s_xor_valid;
    wire [2:0] s_r;
    wire [2:0] s_r_valid;

    reg [5:0] s_in;
    reg [5:0] s_valid_in;
    always @(*) begin
        if (load) begin
            s_in = s_load;
            s_valid_in = s_valid_load;
        end else begin
            s_in[0] = s;
            s_valid_in[0] = s_valid;

            s_in[1] = s_xor[0];
            s_valid_in[1] = s_xor_valid[0];

            s_in[2] = s_r[0];
            s_valid_in[2] = s_r_valid[0];

            s_in[3] = s_xor[1];
            s_valid_in[3] = s_xor_valid[1];

            s_in[4] = s_r[1];
            s_valid_in[4] = s_r_valid[1];

            s_in[5] = s_xor[2];
            s_valid_in[5] = s_xor_valid[2];
        end
    end

    ivn_pe pe0(.clk(clk), .reset(reset), .s(s_in[0]), .s_valid(s_valid_in[0]),
    .s_vn(s_vn[0]), .s_vn_valid(s_vn_valid[0]), .s_xor(s_xor[0]), .s_xor_valid(s_xor_valid[0]),
    .s_r(s_r[0]), .s_r_valid(s_r_valid[0]), .s_store(s_store[0]), .s_valid_store(s_valid_store[0]));
    
    ivn_pe pe1(.clk(clk), .reset(reset), .s(s_in[1]), .s_valid(s_valid_in[1]),
    .s_vn(s_vn[1]), .s_vn_valid(s_vn_valid[1]), .s_xor(s_xor[1]), .s_xor_valid(s_xor_valid[1]),
    .s_r(s_r[1]), .s_r_valid(s_r_valid[1]), .s_store(s_store[1]), .s_valid_store(s_valid_store[1]));

    ivn_pe pe2(.clk(clk), .reset(reset), .s(s_in[2]), .s_valid(s_valid_in[2]),
    .s_vn(s_vn[2]), .s_vn_valid(s_vn_valid[2]), .s_xor(s_xor[2]), .s_xor_valid(s_xor_valid[2]),
    .s_r(s_r[2]), .s_r_valid(s_r_valid[2]), .s_store(s_store[2]), .s_valid_store(s_valid_store[2]));

    ivn_pe pe3(.clk(clk), .reset(reset), .s(s_in[3]), .s_valid(s_valid_in[3]),
    .s_vn(s_vn[3]), .s_vn_valid(s_vn_valid[3]), .s_xor(), .s_xor_valid(),
    .s_r(), .s_r_valid(), .s_store(s_store[3]), .s_valid_store(s_valid_store[3]));

    ivn_pe pe4(.clk(clk), .reset(reset), .s(s_in[4]), .s_valid(s_valid_in[4]),
    .s_vn(s_vn[4]), .s_vn_valid(s_vn_valid[4]), .s_xor(), .s_xor_valid(),
    .s_r(), .s_r_valid(), .s_store(s_store[4]), .s_valid_store(s_valid_store[4]));

    ivn_pe pe5(.clk(clk), .reset(reset), .s(s_in[5]), .s_valid(s_valid_in[5]),
    .s_vn(s_vn[5]), .s_vn_valid(s_vn_valid[5]), .s_xor(), .s_xor_valid(),
    .s_r(), .s_r_valid(), .s_store(s_store[5]), .s_valid_store(s_valid_store[5]));
endmodule


module ivn_pe (
    input clk,
    input reset,
    input s,
    input s_valid,
    output s_vn,
    output s_vn_valid,
    output s_xor,
    output s_xor_valid,
    output s_r,
    output s_r_valid, 
    output s_store,
    output s_valid_store
);
    reg s_reg;
    reg s_valid_reg;

    assign s_store = s_reg;
    assign s_valid_store = s_valid_reg;

    assign s_vn = s_reg;
    assign s_vn_valid = (s_valid_reg && s_valid) && (s_reg !=s);

    assign s_xor = s_reg ^ s;
    assign s_xor_valid = s_valid_reg && s_valid;

    assign s_r = s_reg;
    assign s_r_valid = (s_valid_reg && s_valid) && (s_reg ==s);

    always@(posedge clk) begin
        if (reset) begin
            s_reg <= 0;
            s_valid_reg <= 0;
        end else begin
            s_reg <= s;
            s_valid_reg <= s_valid;
        end
    end
endmodule

code/markov/trng_test.v
`timescale 1ns/1ps
`define NULL 0

module trng_tester();
    reg clk;
    reg reset;
    reg [5:0] valid;
    reg [5:0] bits;

    wire out_valid;
    wire out;
    initial clk = 0;
    initial reset =0;
    always #(10) clk <= ~clk;
	
	reg latch_bit;
    trng dut(
		.clk(clk),
		.reset(reset),
		.latch_bit(latch_bit),
		.out_valid(out_valid),
		.out(out)
	);
	
	
	wire done = 0;
	integer data_file;
	integer scan_file;
    initial begin
        $dumpfile("trng_test1.vcd");
        $dumpvars(0, dut);
        
		data_file = $fopen("out_10ms770mv.txt", "r");
		if (data_file == `NULL) begin
			$display("data_file handle was NULL");
			$finish;
		end
		@(posedge clk);
		reset = 1;
		@(posedge clk);
		reset = 0;
		fork
			begin
				repeat (2500) @(posedge clk);
				if (!done) begin
					$display("Failure: Timing out after 10000 cycles");
					$finish();
				end
			end
		join
		
		$finish;
	end
    
    
	reg [31:0]counter;
    always @(posedge clk) begin
        counter <= counter + 1;
        scan_file = $fscanf(data_file, "%d\n", latch_bit);
        if (scan_file == 0) $finish;
        if (out_valid) begin
            $display("%b", out);
            // $display("%d", test_out);
            // $display("step: %d, out_valid: %d, out: %d, 1out_bit: %d ", counter, out_valid, test_out, out_bit);
        end
    end
       
   
endmodule

code/markov/trng_test1.vcd
$date
	Wed May  5 15:22:22 2021
$end
$version
	Icarus Verilog
$end
$timescale
	1ps
$end
$scope module trng_tester $end
$scope module dut $end
$var wire 1 ! clk $end
$var wire 1 " latch_bit $end
$var wire 1 # reset $end
$var wire 1 $ out_valid $end
$var wire 1 % out $end
$var wire 4 & lane [3:0] $end
$var wire 6 ' ivn_valid [5:0] $end
$var wire 6 ( ivn_out [5:0] $end
$scope module buffer $end
$var wire 1 ! clk $end
$var wire 1 # reset $end
$var wire 1 ) writing $end
$var wire 6 * valid [5:0] $end
$var wire 1 $ out_valid $end
$var wire 1 % out $end
$var wire 5 + counter_wire [4:0] $end
$var wire 5 , counter_up [4:0] $end
$var wire 6 - bits [5:0] $end
$var reg 5 . counter [4:0] $end
$var reg 3 / num_valid [2:0] $end
$var reg 3 0 num_valid_n [2:0] $end
$var reg 1 1 out_valid_reg $end
$var reg 21 2 register [20:0] $end
$var reg 6 3 valid_bits [5:0] $end
$var reg 12 4 write_bits [11:0] $end
$var integer 32 5 idx [31:0] $end
$var integer 32 6 j [31:0] $end
$upscope $end
$scope module ivn $end
$var wire 1 ! clk $end
$var wire 1 # reset $end
$var wire 1 " s $end
$var wire 1 7 s_valid $end
$var wire 6 8 s_vn_valid [5:0] $end
$var wire 6 9 s_vn [5:0] $end
$var wire 6 : s_valid_store [5:0] $end
$var wire 6 ; s_valid_load [5:0] $end
$var wire 6 < s_store [5:0] $end
$var wire 6 = s_load [5:0] $end
$var wire 4 > lane [3:0] $end
$var reg 4 ? current_lane [3:0] $end
$var reg 1 @ load $end
$var reg 2 A next_state [1:0] $end
$var reg 4 B reg_lane [3:0] $end
$var reg 2 C state [1:0] $end
$var reg 1 D wen $end
$scope module ivn_reg $end
$var wire 1 ! clk $end
$var wire 4 E lane [3:0] $end
$var wire 1 # reset $end
$var wire 1 D wen $end
$var wire 6 F s_valid_store [5:0] $end
$var wire 6 G s_valid_load [5:0] $end
$var wire 6 H s_store [5:0] $end
$var wire 6 I s_load [5:0] $end
$upscope $end
$scope module shared_logic $end
$var wire 1 ! clk $end
$var wire 1 @ load $end
$var wire 1 # reset $end
$var wire 1 " s $end
$var wire 6 J s_load [5:0] $end
$var wire 1 7 s_valid $end
$var wire 6 K s_valid_load [5:0] $end
$var wire 3 L s_xor_valid [2:0] $end
$var wire 3 M s_xor [2:0] $end
$var wire 6 N s_vn_valid [5:0] $end
$var wire 6 O s_vn [5:0] $end
$var wire 6 P s_valid_store [5:0] $end
$var wire 6 Q s_store [5:0] $end
$var wire 3 R s_r_valid [2:0] $end
$var wire 3 S s_r [2:0] $end
$var reg 6 T s_in [5:0] $end
$var reg 6 U s_valid_in [5:0] $end
$scope module pe0 $end
$var wire 1 ! clk $end
$var wire 1 # reset $end
$var wire 1 V s $end
$var wire 1 W s_r $end
$var wire 1 X s_r_valid $end
$var wire 1 Y s_store $end
$var wire 1 Z s_valid $end
$var wire 1 [ s_valid_store $end
$var wire 1 \ s_vn $end
$var wire 1 ] s_vn_valid $end
$var wire 1 ^ s_xor $end
$var wire 1 _ s_xor_valid $end
$var reg 1 ` s_reg $end
$var reg 1 a s_valid_reg $end
$upscope $end
$scope module pe1 $end
$var wire 1 ! clk $end
$var wire 1 # reset $end
$var wire 1 b s $end
$var wire 1 c s_r $end
$var wire 1 d s_r_valid $end
$var wire 1 e s_store $end
$var wire 1 f s_valid $end
$var wire 1 g s_valid_store $end
$var wire 1 h s_vn $end
$var wire 1 i s_vn_valid $end
$var wire 1 j s_xor $end
$var wire 1 k s_xor_valid $end
$var reg 1 l s_reg $end
$var reg 1 m s_valid_reg $end
$upscope $end
$scope module pe2 $end
$var wire 1 ! clk $end
$var wire 1 # reset $end
$var wire 1 n s $end
$var wire 1 o s_r $end
$var wire 1 p s_r_valid $end
$var wire 1 q s_store $end
$var wire 1 r s_valid $end
$var wire 1 s s_valid_store $end
$var wire 1 t s_vn $end
$var wire 1 u s_vn_valid $end
$var wire 1 v s_xor $end
$var wire 1 w s_xor_valid $end
$var reg 1 x s_reg $end
$var reg 1 y s_valid_reg $end
$upscope $end
$scope module pe3 $end
$var wire 1 ! clk $end
$var wire 1 # reset $end
$var wire 1 z s $end
$var wire 1 { s_r $end
$var wire 1 | s_r_valid $end
$var wire 1 } s_store $end
$var wire 1 ~ s_valid $end
$var wire 1 !" s_valid_store $end
$var wire 1 "" s_vn $end
$var wire 1 #" s_vn_valid $end
$var wire 1 $" s_xor $end
$var wire 1 %" s_xor_valid $end
$var reg 1 &" s_reg $end
$var reg 1 '" s_valid_reg $end
$upscope $end
$scope module pe4 $end
$var wire 1 ! clk $end
$var wire 1 # reset $end
$var wire 1 (" s $end
$var wire 1 )" s_r $end
$var wire 1 *" s_r_valid $end
$var wire 1 +" s_store $end
$var wire 1 ," s_valid $end
$var wire 1 -" s_valid_store $end
$var wire 1 ." s_vn $end
$var wire 1 /" s_vn_valid $end
$var wire 1 0" s_xor $end
$var wire 1 1" s_xor_valid $end
$var reg 1 2" s_reg $end
$var reg 1 3" s_valid_reg $end
$upscope $end
$scope module pe5 $end
$var wire 1 ! clk $end
$var wire 1 # reset $end
$var wire 1 4" s $end
$var wire 1 5" s_r $end
$var wire 1 6" s_r_valid $end
$var wire 1 7" s_store $end
$var wire 1 8" s_valid $end
$var wire 1 9" s_valid_store $end
$var wire 1 :" s_vn $end
$var wire 1 ;" s_vn_valid $end
$var wire 1 <" s_xor $end
$var wire 1 =" s_xor_valid $end
$var reg 1 >" s_reg $end
$var reg 1 ?" s_valid_reg $end
$upscope $end
$upscope $end
$upscope $end
$scope module router $end
$var wire 1 " bit_in $end
$var wire 1 @" bit_out $end
$var wire 1 ! clk $end
$var wire 4 A" lane [3:0] $end
$var wire 1 # reset $end
$var reg 4 B" next_state [3:0] $end
$var reg 4 C" state [3:0] $end
$upscope $end
$upscope $end
$upscope $end
$enddefinitions $end
#0
$dumpvars
bx C"
bx B"
bx A"
x@"
x?"
x>"
x="
x<"
x;"
x:"
x9"
x8"
x7"
x6"
x5"
x4"
x3"
x2"
x1"
x0"
x/"
x."
x-"
x,"
x+"
x*"
x)"
x("
x'"
x&"
x%"
x$"
x#"
x""
x!"
x~
x}
x|
x{
xz
xy
xx
xw
xv
xu
xt
xs
xr
xq
xp
xo
xn
xm
xl
xk
xj
xi
xh
xg
xf
xe
xd
xc
xb
xa
x`
x_
x^
x]
x\
x[
1Z
xY
xX
xW
xV
bx1 U
bx T
bx S
bx R
bx Q
bx P
bx O
bx N
bx M
bx L
bx K
bx J
bx I
bx H
bx G
bx F
bx E
xD
bx C
bx B
bx A
x@
bx ?
bx >
bx =
bx <
bx ;
bx :
bx 9
bx 8
17
bx 6
bx 5
bx 4
bx 3
bx 2
x1
bx 0
bx /
bx .
bx -
bx ,
bx +
bx *
x)
bx (
bx '
bx &
x%
x$
0#
x"
0!
$end
#10000
1$"
1z
0<"
04"
0,"
0r
1j
08"
0~
0f
1b
00"
0v
b110 0
0X
0]
0d
0i
b0 R
0p
b1 U
0u
0("
0n
0|
0#"
0*"
0/"
06"
b0 '
b0 *
b0 8
b0 N
0;"
0)
0_
b11 M
1^
0k
b0 L
0w
0%"
01"
0="
b0 4
b110 5
b0 3
b0 /
b0 A
0@
0D
0%
b0 &
b0 >
b0 A"
b0 C"
0[
0a
0W
0\
0Y
0`
0g
0m
0c
0h
0e
0l
0s
0y
b0 S
0o
0t
0q
0x
0!"
0'"
0{
0""
0}
0&"
0-"
03"
0)"
0."
0+"
02"
b0 :
b0 F
b0 P
09"
0?"
05"
b0 (
b0 -
b0 9
b0 O
0:"
b0 <
b0 H
b0 Q
07"
0>"
b0 ?
b0 C
01
b0 2
b0 .
1V
b0 +
b0 ,
0$
b1011 T
b1 B"
1#
1@"
1"
1!
#20000
0!
#30000
b0 B"
b101 ,
0#
1!
#40000
0!
#50000
1<"
14"
1)
1f
b1 4
b101 0
b1 3
b1 /
10"
1v
b11 U
b1 '
b1 *
b1 8
b1 N
1]
1("
1n
b1 L
1_
b110 5
b1 :
b1 F
b1 P
1[
1a
1W
1\
1Y
1`
b11 S
1c
1h
1e
1l
1{
b1011 (
b1011 -
b1011 9
b1011 O
1""
b1011 <
b1011 H
b1011 Q
1}
1&"
1$"
0z
0j
1b
b101 M
1^
0V
b110110 T
b0 6
0@"
0"
1!
#60000
0!
#70000
0,"
1z
1i
14"
1~
1r
1j
b101 0
0d
b1111 U
b1 R
1X
0n
0b
b10 '
b10 *
b10 8
b10 N
0]
1)
1$
1%
0<"
00"
1$"
1v
b11 L
1k
b111000 T
b110 M
0^
b1 4
b110 5
b1 3
b1 /
11
b1 2
15"
1:"
17"
1>"
1)"
1."
1+"
12"
0{
0""
0}
0&"
1o
1t
1q
1x
b11 :
b11 F
b11 P
1g
1m
b110 S
0W
b110110 (
b110110 -
b110110 9
b110110 O
0\
b110110 <
b110110 H
b110110 Q
0Y
0`
b1 6
1!
#80000
0!
#90000
1#"
1,"
b101 0
18"
0z
1<"
10"
1d
b1000 '
b1000 *
b1000 8
b1000 N
0i
b111111 U
b111 R
1p
04"
0("
0|
1)
0j
b111 L
1w
b0 T
b0 M
0v
1%"
1$"
b1 4
b110 5
b1 3
b1 /
0c
0h
0e
0l
1s
1y
b0 S
0o
0t
0q
0x
b1111 :
b1111 F
b1111 P
1!"
1'"
1{
b111000 (
b111000 -
b111000 9
b111000 O
1""
b111000 <
b111000 H
b111000 Q
1}
1&"
b1 6
1!
#100000
0!
#110000
0<"
00"
19"
1?"
05"
0:"
07"
0>"
b111111 :
b111111 F
b111111 P
1-"
13"
0)"
0."
0+"
02"
0{
b0 (
b0 -
b0 9
b0 O
0""
b0 <
b0 H
b0 Q
0}
0&"
1#"
0|
1$"
08"
0,"
1z
0p
1i
0d
0)
b11 L
0w
1j
b0 4
b11 0
b110 5
b0 3
b11 /
0r
1b
b1011 '
b1011 *
b1011 8
b1011 N
1]
b1011 U
b0 R
0X
b11 M
1^
1V
b1011 T
b1 B"
1@"
1"
b1 6
1!
#120000
0!
#130000
1<"
14"
1)
10"
1v
b11 4
b11 3
1("
1n
b1 A
b10 +
b111 ,
0%
b1 &
b1 >
b1 A"
b1 C"
1W
1\
1Y
1`
b11 S
1c
1h
1e
1l
0s
0y
1{
b1011 (
b1011 -
b1011 9
b1011 O
1""
b1011 <
b1011 H
b1011 Q
1}
1&"
0-"
03"
b1011 :
b1011 F
b1011 P
09"
0?"
b10 .
b0 2
06"
0*"
1#"
0|
0="
01"
1$"
08"
1,"
0z
0p
0i
1d
b11 L
0w
0j
b100 0
b110 5
b10 /
0r
1b
b1001 '
b1001 *
b1001 8
b1001 N
1]
b11011 U
b10 R
0X
b101 M
1^
0V
b110110 T
b10 B"
b11 6
0@"
0"
1!
#140000
0!
#150000
0,"
1z
1i
0d
14"
1r
1j
b100 0
0*"
0|
1#"
b1111 U
b1 R
1X
0n
0b
b1010 '
b1010 *
b1010 8
b1010 N
0]
1)
b0 =
b0 I
b0 J
b0 ;
b0 G
b0 K
b11 +
b1000 ,
0<"
01"
00"
1$"
1v
b111000 T
b110 M
0^
b1 4
b110 5
b1 3
b10 /
b100 B"
b10 A
1D
b0 B
b0 E
b11 .
b1100 2
b1 C
15"
1:"
17"
1>"
b11011 :
b11011 F
b11011 P
1-"
13"
1)"
1."
1+"
12"
0{
0""
0}
0&"
1o
1t
1q
1x
b110 S
0W
b110110 (
b110110 -
b110110 9
b110110 O
0\
b110110 <
b110110 H
b110110 Q
0Y
0`
b10 &
b10 >
b10 A"
b10 C"
b10 6
1!
#160000
0!
#170000
0_
b0 L
0k
0%"
10"
1<"
0Z
0f
0~
0("
04"
0v
b0 A
1@
0D
b100 B
b100 E
b100 +
b1001 ,
b100 &
b100 >
b100 A"
b100 C"
0c
0h
0e
0l
1s
1y
b0 S
0o
0t
0q
0x
1{
b111000 (
b111000 -
b111000 9
b111000 O
1""
b111000 <
b111000 H
b111000 Q
1}
1&"
b1111 :
b1111 F
b1111 P
0-"
03"
b10 C
b100 .
b1110 2
0*"
0#"
0|
01"
1$"
0,"
0z
0i
0d
0)
0j
b0 4
b110 0
b110 5
b0 3
b0 /
0r
0b
b0 '
b0 *
b0 8
b0 N
0]
b0 U
b0 R
0X
b0 M
0^
0V
b0 T
b1001 B"
b10 6
1@"
1"
1!
#180000
0!
#190000
1Z
b1 U
b11 +
b1000 ,
1%
0<"
00"
0$"
b110 5
b1 A
0@
b11 .
b111 2
b100 ?
b0 C
05"
0:"
07"
0>"
0)"
0."
0+"
02"
0!"
0'"
0{
b0 (
b0 -
b0 9
b0 O
0""
b0 <
b0 H
b0 Q
0}
0&"
0s
0y
0g
0m
b0 :
b0 F
b0 P
0[
0a
b1001 &
b1001 >
b1001 A"
b1001 C"
b10 B"
0@"
0"
b100 6
1!
#200000
0!
#210000
1f
b101 0
b1 /
b110 5
b11 U
b1 '
b1 *
b1 8
b1 N
1]
b1 L
1_
b10 A
1D
b10 +
b111 ,
b10 &
b10 >
b10 A"
b10 C"
b1 :
b1 F
b1 P
1[
1a
b1 C
b10 .
b11 2
1$"
1z
1j
1b
b11 M
1^
1V
b1011 T
b101 B"
b11 6
1@"
1"
1!
#220000
0!
#230000
0)
0_
b0 4
b0 3
0i
0Z
0f
b0 L
0k
b0 A
1@
0D
b101 B
b101 E
b1 2
b10 C
1{
1""
1}
1&"
b11 :
b11 F
b11 P
1g
1m
1c
1h
1e
1l
b11 S
1W
b1011 (
b1011 -
b1011 9
b1011 O
1\
b1011 <
b1011 H
b1011 Q
1Y
1`
b101 &
b101 >
b101 A"
b101 C"
1$"
0z
1j
b110 0
b110 5
b0 /
0r
0b
b0 '
b0 *
b0 8
b0 N
0]
b0 U
b0 R
0X
b11 M
1^
0V
b0 T
b1010 B"
0@"
0"
b1 6
1!
#240000
0!
#250000
1z
1b
1Z
1V
1^
b1 U
b1011 T
b11 M
1j
1$"
b110 5
b1 A
0@
b1 +
b110 ,
0%
b1010 &
b1010 >
b1010 A"
b1010 C"
0[
0a
0W
0\
0Y
0`
b0 :
b0 F
b0 P
0g
0m
b0 S
0c
0h
0e
0l
0{
b0 (
b0 -
b0 9
b0 O
0""
b0 <
b0 H
b0 Q
0}
0&"
b101 ?
b0 C
b1 .
b0 2
b101 B"
b10 6
1@"
1"
1!
#260000
0!
#270000
1<"
14"
1)
1f
10"
1v
b1 4
b101 0
b1 3
b1 /
b11 U
1("
1n
b1 '
b1 *
b1 8
b1 N
1]
b0 +
b101 ,
b1 L
1_
b110 5
b10 A
1D
b0 .
b1 C
1{
1""
1}
1&"
1c
1h
1e
1l
b1 :
b1 F
b1 P
1[
1a
b11 S
1W
b1011 (
b1011 -
b1011 9
b1011 O
1\
b1011 <
b1011 H
b1011 Q
1Y
1`
b101 &
b101 >
b101 A"
b101 C"
1$"
0z
0j
1b
b101 M
1^
0V
b110110 T
b1010 B"
0@"
0"
b1 6
1!
#280000
0!
#290000
0_
0i
0Z
0f
0n
0("
04"
b0 L
0k
1v
10"
1<"
b0 A
1@
0D
b1010 B
b1010 E
1%
b1010 &
b1010 >
b1010 A"
b1010 C"
0W
0\
0Y
0`
b11 :
b11 F
b11 P
1g
1m
b110 S
1o
1t
1q
1x
0{
0""
0}
0&"
1)"
1."
1+"
12"
15"
b110110 (
b110110 -
b110110 9
b110110 O
1:"
b110110 <
b110110 H
b110110 Q
17"
1>"
b10 C
b1 2
0$"
0z
0)
1j
b0 4
b110 0
b110 5
b0 3
b0 /
0r
0b
b0 '
b0 *
b0 8
b0 N
0]
b0 U
b0 R
0X
b110 M
0^
0V
b0 T
b101 B"
b1 6
1@"
1"
1!
#300000
0!
#310000
1$"
1z
1b
1^
04"
1Z
1V
0$
0<"
00"
0v
b1 U
b1011 T
b11 M
1j
b110 5
b1011 B"
b1 A
0@
01
b1010 ?
b0 C
05"
0:"
07"
0>"
0)"
0."
0+"
02"
0o
0t
0q
0x
0g
0m
b0 S
0c
b0 (
b0 -
b0 9
b0 O
0h
b0 <
b0 H
b0 Q
0e
0l
b0 :
b0 F
b0 P
0[
0a
b101 &
b101 >
b101 A"
b101 C"
b0 6
1!
#320000
0!
